dynareadout.pypy39-pp73-x86_64-linux-gnu.so
lib/pybind11/LICENSE
lib/pybind11/setup.py
lib/pybind11/noxfile.py
lib/pybind11/pybind11/__init__.py
lib/pybind11/pybind11/py.typed
lib/pybind11/pybind11/_version.py
lib/pybind11/pybind11/commands.py
lib/pybind11/pybind11/setup_helpers.py
lib/pybind11/pybind11/__main__.py
lib/pybind11/tools/libsize.py
lib/pybind11/tools/make_changelog.py
lib/pybind11/tools/codespell_ignore_lines_from_errors.py
lib/pybind11/tests/test_opaque_types.py
lib/pybind11/tests/test_factory_constructors.py
lib/pybind11/tests/test_exceptions.py
lib/pybind11/tests/test_smart_ptr.py
lib/pybind11/tests/test_stl.py
lib/pybind11/tests/test_vector_unique_ptr_member.py
lib/pybind11/tests/test_multiple_inheritance.py
lib/pybind11/tests/test_operator_overloading.py
lib/pybind11/tests/test_call_policies.py
lib/pybind11/tests/test_numpy_dtypes.py
lib/pybind11/tests/test_numpy_vectorize.py
lib/pybind11/tests/test_custom_type_setup.py
lib/pybind11/tests/test_pytypes.py
lib/pybind11/tests/test_buffers.py
lib/pybind11/tests/test_copy_move.py
lib/pybind11/tests/test_python_multiple_inheritance.py
lib/pybind11/tests/env.py
lib/pybind11/tests/test_sequences_and_iterators.py
lib/pybind11/tests/conftest.py
lib/pybind11/tests/test_virtual_functions.py
lib/pybind11/tests/test_callbacks.py
lib/pybind11/tests/test_chrono.py
lib/pybind11/tests/test_numpy_array.py
lib/pybind11/tests/test_eval.py
lib/pybind11/tests/test_pickling.py
lib/pybind11/tests/test_builtin_casters.py
lib/pybind11/tests/test_class.py
lib/pybind11/tests/test_unnamed_namespace_b.py
lib/pybind11/tests/test_const_name.py
lib/pybind11/tests/test_iostream.py
lib/pybind11/tests/test_unnamed_namespace_a.py
lib/pybind11/tests/test_eigen_matrix.py
lib/pybind11/tests/test_type_caster_pyobject_ptr.py
lib/pybind11/tests/test_custom_type_casters.py
lib/pybind11/tests/test_kwargs_and_defaults.py
lib/pybind11/tests/test_docstring_options.py
dynareadout-24.7.dist-info/LICENSE
dynareadout-24.7.dist-info/WHEEL
dynareadout-24.7.dist-info/top_level.txt
dynareadout-24.7.dist-info/RECORD
dynareadout-24.7.dist-info/METADATA
