Metadata-Version: 2.1
Name: dynareadout
Version: 24.7
Summary: High-Performance and Thread-Safe library for parsing binary output files and key files of LS Dyna (d3plot, binout, input deck)
Author-email: PucklaJ <kassandra@pucher.space>
Project-URL: Homepage, https://github.com/PucklaJ/dynareadout
Project-URL: Bug Trackers, https://github.com/PucklaJ/dynareadout/issues
Classifier: Programming Language :: C
Classifier: Programming Language :: C++
Classifier: License :: OSI Approved :: zlib/libpng License
Classifier: Operating System :: Microsoft :: Windows
Classifier: Operating System :: MacOS
Classifier: Operating System :: POSIX :: Linux
Classifier: Topic :: Scientific/Engineering
Requires-Python: >=3.6
License-File: LICENSE
